MANIFEST.in
README.rst
latex2markdown.py
setup.py
latex2markdown.egg-info/PKG-INFO
latex2markdown.egg-info/SOURCES.txt
latex2markdown.egg-info/dependency_links.txt
latex2markdown.egg-info/top_level.txt