Metadata-Version: 1.0
Name: latex2markdown
Version: 0.1.2
Summary: An AMSTeX compatible converter that maps a subset of AMSTeX and LaTeX to Markdown/MathJaX.
Home-page: https://github.com/ajtulloch/LaTeX2Markdown
Author: Andrew Tulloch
Author-email: andrew@tullo.ch
License: UNKNOWN
Platform: UNKNOWN
Classifier: Development Status :: 3 - Alpha
Classifier: Environment :: Console
Classifier: Programming Language :: Python
Classifier: Topic :: Scientific/Engineering :: Mathematics
Classifier: Topic :: Software Development :: Documentation
Classifier: Topic :: Text Processing :: Markup
Classifier: Topic :: Text Processing :: Markup :: LaTeX
Classifier: Topic :: Text Processing :: Markup :: HTML
